pygameyagui/__init__.py
pygameyagui/__main__.py
pygameyagui/pygameyagui.png
pygameyagui/base/chart.py
pygameyagui/base/interval.py
pygameyagui/base/numeric.py
pygameyagui/base/toolbox.py
pygameyagui/base/variables.py
pygameyagui/base/widget.py
pygameyagui/include/constants.py
pygameyagui/include/draw.py
pygameyagui/include/error.py
pygameyagui/include/tools.py
pygameyagui/input/button.py
pygameyagui/input/button_icon.py
pygameyagui/input/checkbox.py
pygameyagui/input/menu_item.py
pygameyagui/input/numeric_input.py
pygameyagui/input/radio_button.py
pygameyagui/input/slider.py
pygameyagui/input/slider_float.py
pygameyagui/input/slider_int.py
pygameyagui/output/label.py
pygameyagui/output/numeric_output.py
pygameyagui/output/sparkline.py
pygameyagui/output/tank_meter.py
pygameyagui-0.3.dist-info/LICENSE
pygameyagui-0.3.dist-info/WHEEL
pygameyagui-0.3.dist-info/METADATA
pygameyagui-0.3.dist-info/RECORD
