Metadata-Version: 2.1
Name: pygameyagui
Version: 0.3
Summary: Pygame-YaGUI is Yet another GUI for Pygame.
Author-email: Alexandre Maciel <acmaciel@ufpi.edu.br>
Requires-Dist: sphinx ; extra == "doc"
Requires-Dist: myst-parser ; extra == "doc"
Requires-Dist: sphinx-copybutton ; extra == "doc"
Requires-Dist: sphinx-sizzle-theme ; extra == "doc"
Project-URL: Home, https://pygameyagui.readthedocs.io/
Provides-Extra: doc
